icore/__init__.py
icore/abs_model.py
icore/abs_model_test.py
icore/db_config.py
icore/db_config_test.py
icore/icmp.py
icore/illi.py
icore/vo.py
icore-1.0.10.dist-info/LICENSE
icore-1.0.10.dist-info/METADATA
icore-1.0.10.dist-info/WHEEL
icore-1.0.10.dist-info/top_level.txt
icore-1.0.10.dist-info/RECORD
