Metadata-Version: 2.1
Name: icore
Version: 1.0.10
Summary: Modulo de icore.
Home-page: https://github.com/illimitar/icore.git
Author: Hermílio Alves
Author-email: hermilio@illimitar.com.br
Classifier: Programming Language :: Python :: 3
Classifier: License :: OSI Approved :: MIT License
Classifier: Operating System :: OS Independent
Requires-Python: >=3.10
License-File: LICENSE
Requires-Dist: dash
Requires-Dist: pandas
Requires-Dist: dash-mantine-components
Requires-Dist: elastic-apm
Requires-Dist: dash-iconify
Requires-Dist: dash-ag-grid
Requires-Dist: sqlalchemy
Requires-Dist: pymssql
Requires-Dist: mysql-connector-python
Requires-Dist: blinker
Requires-Dist: gunicorn
